vislparser/__init__.py
vislparser/vislparser.py
vislparser-0.0.5.dist-info/LICENSE
vislparser-0.0.5.dist-info/METADATA
vislparser-0.0.5.dist-info/WHEEL
vislparser-0.0.5.dist-info/top_level.txt
vislparser-0.0.5.dist-info/RECORD
