Metadata-Version: 2.1
Name: vislparser
Version: 0.0.5
Summary: Automatic calls to VISL online parser
Home-page: https://github.com/lplnufpi/vislparser
Author: José Patrício
Author-email: jpegx100@gmail.com
License: UNKNOWN
Platform: UNKNOWN
Classifier: Programming Language :: Python :: 3
Classifier: License :: OSI Approved :: MIT License
Classifier: Operating System :: OS Independent
Requires-Dist: lxml (==4.2.5)
Requires-Dist: requests (==2.21.0)
Requires-Dist: urllib3 (==1.24.1)
